goodutils/__init__.py
goodutils/goodutilssourcecode.py
goodutils-0.1.5.dist-info/METADATA
goodutils-0.1.5.dist-info/WHEEL
goodutils-0.1.5.dist-info/top_level.txt
goodutils-0.1.5.dist-info/RECORD
