Metadata-Version: 2.4
Name: goodutils
Version: 0.1.5
Summary: Utils you can't refuse
Author-email: steve <steve@bootladder.com>
License: MIT
Classifier: Programming Language :: Python :: 3
Classifier: License :: OSI Approved :: MIT License
Classifier: Operating System :: OS Independent
Requires-Python: >=3.8
Requires-Dist: requests>=2.25.0
